Metadata-Version: 2.1
Name: hello-world-suarim-suar
Version: 0.1.0
Summary: A simple Hello, World! package with classes
Home-page: https://github.com/yourusername/hello-world
Author: Your Name
Author-email: your.email@example.com
Classifier: Programming Language :: Python :: 3
Classifier: License :: OSI Approved :: MIT License
Classifier: Operating System :: OS Independent
Requires-Python: >=3.6
